[
  {
    "id": "1",
    "points": [[120, 175], [8, 260], [44, 295], [159, 200]]
  },
  {
    "id": "2",
    "points": [[225, 176], [119, 265], [165, 306], [277, 203]]
  },
  {
    "id": "3",
    "points": [[335, 180], [240, 273], [308, 313], [390, 207]]
  },
  {
    "id": "4",
    "points": [[442, 182], [368, 278], [447, 312], [502, 211]]
  },
  {
    "id": "5",
    "points": [[546, 184], [492, 278], [578, 311], [605, 211]]
  },
  {
    "id": "6",
    "points": [[515, 83], [482, 134], [536, 158], [562, 101]]
  },
  {
    "id": "7",
    "points": [[484, 95], [440, 152], [387, 129], [432, 80]]
  },
  {
    "id": "8",
    "points": [[398, 89], [336, 145], [288, 122], [350, 77]]
  },
  {
    "id": "9",
    "points": [[303, 86], [233, 143], [190, 125], [264, 74]]
  },
  {
    "id": "10",
    "points": [[222, 81], [129, 146], [91, 128], [179, 72]]
  }
]
  